webfilecast/__init__.py
webfilecast/logger.py
webfilecast-1.1.4.dist-info/licenses/LICENSE
webfilecast-1.1.4.dist-info/METADATA
webfilecast-1.1.4.dist-info/WHEEL
webfilecast-1.1.4.dist-info/entry_points.txt
webfilecast-1.1.4.dist-info/top_level.txt
webfilecast-1.1.4.dist-info/RECORD
