Metadata-Version: 2.4
Name: webfilecast
Version: 1.1.4
Summary: Webfrontend to cast local videos to your chromecast
Author-email: Johannes Paul <vanadinit@quantentunnel.de>
License: MIT
Project-URL: Homepage, https://github.com/vanadinit/webfilecast
Keywords: Chromecast,video,local,movie,terminalcast
Classifier: Programming Language :: Python :: 3
Classifier: License :: OSI Approved :: MIT License
Requires-Python: >=3.10
License-File: LICENSE
Requires-Dist: terminalcast>=1.3.2
Requires-Dist: Flask
Requires-Dist: redis
Requires-Dist: flask_socketio
Requires-Dist: filetype>=1.0.0
Requires-Dist: rq
Provides-Extra: deployment
Requires-Dist: gunicorn; extra == "deployment"
Requires-Dist: eventlet; extra == "deployment"
Dynamic: license-file
